zensols/actioncli/__init__.py
zensols/actioncli/config.py
zensols/actioncli/executor.py
zensols/actioncli/factory.py
zensols/actioncli/log.py
zensols/actioncli/multi.py
zensols/actioncli/peraction.py
zensols/actioncli/persist.py
zensols/actioncli/simple.py
zensols/actioncli/stash_factory.py
zensols/actioncli/tempfile.py
zensols/actioncli/time.py
zensols/actioncli/yaml_config.py
zensols.actioncli-1.1.5.dist-info/LICENSE.txt
zensols.actioncli-1.1.5.dist-info/METADATA
zensols.actioncli-1.1.5.dist-info/WHEEL
zensols.actioncli-1.1.5.dist-info/top_level.txt
zensols.actioncli-1.1.5.dist-info/RECORD
