Metadata-Version: 2.1
Name: zensols.actioncli
Version: 1.1.5
Summary: This library intends to make command line execution and configuration easy.
Home-page: https://github.com/plandes/actioncli
Author: Paul Landes
Author-email: landes@mailc.net
License: UNKNOWN
Download-URL: https://github.com/plandes/actioncli/releases/download/v1.1.5/zensols.actioncli-1.1.5-py3-none-any.whl
Keywords: tooling,command line
Platform: UNKNOWN
Requires-Dist: configparser (==3.5.0)
Requires-Dist: PyYAML (>=5.1)
Requires-Dist: parse (>=1.9.0)
